Workbook

Sheet Simulador
B1: SIMULADOR DE INVESTIMENTOS EM FUNDOS IMOBILIÁRIOS
B4: 1. SEUS DADOS
B5: Quanto investir por mês | C5: 1000 | D5: Sugestão (30% do salário): | E5: =aporte_sugerido -> 1500
B6: Por quantos anos | C6: 20
B7: Taxa de rendimento mensal | C7: =taxa_mensal -> 0.008 | D7: (altere em Configurações)
B9: 2. RESULTADOS
B10: Patrimônio acumulado | C10: =FV(taxa_mensal,anos*12,-aporte) -> 721131.22
B11: Total investido (do seu bolso) | C11: =aporte*anos*12 -> 240000
B12: Dividendos por mês | C12: =patrimonio*taxa_mensal -> 5769.0498
B14: 3. CENÁRIOS DE 2 A 30 ANOS (mesmo aporte e taxa)
B15: Anos | C15: Total investido | D15: Patrimônio | E15: Dividendos/mês
B16: 2 | C16: =aporte*$B16*12 -> 24000 | D16: =FV(taxa_mensal,$B16*12,-aporte) -> 26343.155 | E16: =D16*taxa_mensal -> 210.74524
B17: 5 | C17: =aporte*$B17*12 -> 60000 | D17: =FV(taxa_mensal,$B17*12,-aporte) -> 76623.867 | E17: =D17*taxa_mensal -> 612.99093
B18: 10 | C18: =aporte*$B18*12 -> 120000 | D18: =FV(taxa_mensal,$B18*12,-aporte) -> 200217.47 | E18: =D18*taxa_mensal -> 1601.7398
B19: 20 | C19: =aporte*$B19*12 -> 240000 | D19: =FV(taxa_mensal,$B19*12,-aporte) -> 721131.22 | E19: =D19*taxa_mensal -> 5769.0498
B20: 30 | C20: =aporte*$B20*12 -> 360000 | D20: =FV(taxa_mensal,$B20*12,-aporte) -> 2076413.2 | E20: =D20*taxa_mensal -> 16611.306
B22: 4. DIVISÃO DO APORTE POR PERFIL
B23: Perfil de investidor | C23: Moderado
B25: Tipo de fundo | C25: % do aporte | D25: Valor por mês
B26: Papel (CRI) | C26: =VLOOKUP(perfil&"|"&$B26,Apoio!$A$2:$D$19,4,FALSE()) -> 0.25 | D26: =aporte*C26 -> 250
B27: Logística | C27: =VLOOKUP(perfil&"|"&$B27,Apoio!$A$2:$D$19,4,FALSE()) -> 0.2 | D27: =aporte*C27 -> 200
B28: Shoppings | C28: =VLOOKUP(perfil&"|"&$B28,Apoio!$A$2:$D$19,4,FALSE()) -> 0.2 | D28: =aporte*C28 -> 200
B29: Lajes corporativas | C29: =VLOOKUP(perfil&"|"&$B29,Apoio!$A$2:$D$19,4,FALSE()) -> 0.1 | D29: =aporte*C29 -> 100
B30: Fundo de fundos | C30: =VLOOKUP(perfil&"|"&$B30,Apoio!$A$2:$D$19,4,FALSE()) -> 0.15 | D30: =aporte*C30 -> 150
B31: Desenvolvimento | C31: =VLOOKUP(perfil&"|"&$B31,Apoio!$A$2:$D$19,4,FALSE()) -> 0.1 | D31: =aporte*C31 -> 100
B32: Total | C32: =SUM(C26:C31) -> 1 | D32: =SUM(D26:D31) -> 1000
B34: Legenda: amarelo = editar (aporte, anos, perfil); cinza = calculado, não edite. Taxa, salário e sugestão ficam em Configurações. Percentuais por perfil são exemplo, não recomendação de investimento.

Sheet Configurações
A1: CONFIGURAÇÕES
A3: Salário mensal | B3: 5000 | C3: Exemplo: substitua pelo seu salário.
A4: Rendimento mensal da carteira (taxa_mensal) | B4: 0.008 | C4: Exemplo de 0,80% ao mês; substitua pela taxa que você espera.
A5: % do salário sugerido para investir | B5: 0.3 | C5: Sugestão de 30% do salário.
A6: Aporte sugerido (aporte_sugerido) | B6: =B3*B5 -> 1500 | C6: Calculado: salário × percentual sugerido.
A8: Legenda: células amarelas (letra azul) são para editar; cinzas são calculadas.

Sheet Apoio
A1: Chave (perfil|tipo) | B1: Perfil | C1: Tipo de fundo | D1: Percentual | F1: Perfil | G1: Soma
A2: =B2&"|"&C2 -> Conservador|Papel (CRI) | B2: Conservador | C2: Papel (CRI) | D2: 0.4 | F2: Conservador | G2: =SUMIF($B$2:$B$19,F2,$D$2:$D$19) -> 1
A3: =B3&"|"&C3 -> Conservador|Logística | B3: Conservador | C3: Logística | D3: 0.2 | F3: Moderado | G3: =SUMIF($B$2:$B$19,F3,$D$2:$D$19) -> 1
A4: =B4&"|"&C4 -> Conservador|Shoppings | B4: Conservador | C4: Shoppings | D4: 0.1 | F4: Arrojado | G4: =SUMIF($B$2:$B$19,F4,$D$2:$D$19) -> 1
A5: =B5&"|"&C5 -> Conservador|Lajes corporativas | B5: Conservador | C5: Lajes corporativas | D5: 0.1
A6: =B6&"|"&C6 -> Conservador|Fundo de fundos | B6: Conservador | C6: Fundo de fundos | D6: 0.15 | F6: Lista de perfis
A7: =B7&"|"&C7 -> Conservador|Desenvolvimento | B7: Conservador | C7: Desenvolvimento | D7: 0.05 | F7: Conservador
A8: =B8&"|"&C8 -> Moderado|Papel (CRI) | B8: Moderado | C8: Papel (CRI) | D8: 0.25 | F8: Moderado
A9: =B9&"|"&C9 -> Moderado|Logística | B9: Moderado | C9: Logística | D9: 0.2 | F9: Arrojado
A10: =B10&"|"&C10 -> Moderado|Shoppings | B10: Moderado | C10: Shoppings | D10: 0.2
A11: =B11&"|"&C11 -> Moderado|Lajes corporativas | B11: Moderado | C11: Lajes corporativas | D11: 0.1
A12: =B12&"|"&C12 -> Moderado|Fundo de fundos | B12: Moderado | C12: Fundo de fundos | D12: 0.15
A13: =B13&"|"&C13 -> Moderado|Desenvolvimento | B13: Moderado | C13: Desenvolvimento | D13: 0.1
A14: =B14&"|"&C14 -> Arrojado|Papel (CRI) | B14: Arrojado | C14: Papel (CRI) | D14: 0.15
A15: =B15&"|"&C15 -> Arrojado|Logística | B15: Arrojado | C15: Logística | D15: 0.2
A16: =B16&"|"&C16 -> Arrojado|Shoppings | B16: Arrojado | C16: Shoppings | D16: 0.25
A17: =B17&"|"&C17 -> Arrojado|Lajes corporativas | B17: Arrojado | C17: Lajes corporativas | D17: 0.15
A18: =B18&"|"&C18 -> Arrojado|Fundo de fundos | B18: Arrojado | C18: Fundo de fundos | D18: 0.1
A19: =B19&"|"&C19 -> Arrojado|Desenvolvimento | B19: Arrojado | C19: Desenvolvimento | D19: 0.15
A21: Percentuais são apenas um exemplo, não recomendação de investimento. Edite a coluna D (azul); cada perfil deve somar 100%.
